cli/__init__.py
cli/main.py
core/__init__.py
core/config.py
formatters/__init__.py
formatters/output_formatter.py
generators/__init__.py
generators/poc_generator.py
generators/shellcode_generator.py
parsers/__init__.py
parsers/cve_parser.py
utils/__init__.py
utils/merge_model.py
pocsmith-1.0.0.dist-info/METADATA
pocsmith-1.0.0.dist-info/WHEEL
pocsmith-1.0.0.dist-info/entry_points.txt
pocsmith-1.0.0.dist-info/top_level.txt
pocsmith-1.0.0.dist-info/RECORD
