Metadata-Version: 2.4
Name: pocsmith
Version: 1.0.0
Summary: AI-powered exploit and shellcode generation for security research
Home-page: https://github.com/noobforanonymous/PoCSmith
Author: Regaan
Author-email: regaan48@gmail.com
Classifier: Development Status :: 4 - Beta
Classifier: Intended Audience :: Information Technology
Classifier: Topic :: Security
Classifier: Programming Language :: Python :: 3.11
Classifier: Programming Language :: Python :: 3.12
Requires-Python: >=3.11
Requires-Dist: torch>=2.0.0
Requires-Dist: transformers>=4.35.0
Requires-Dist: peft>=0.7.0
Requires-Dist: bitsandbytes>=0.41.0
Requires-Dist: accelerate>=0.24.0
Requires-Dist: click>=8.1.0
Requires-Dist: requests>=2.31.0
Requires-Dist: rich>=13.0.0
Provides-Extra: dev
Requires-Dist: pytest>=7.4.0; extra == "dev"
Requires-Dist: black>=23.0.0; extra == "dev"
Requires-Dist: ruff>=0.1.0; extra == "dev"
Dynamic: author
Dynamic: author-email
Dynamic: classifier
Dynamic: description
Dynamic: description-content-type
Dynamic: home-page
Dynamic: provides-extra
Dynamic: requires-dist
Dynamic: requires-python
Dynamic: summary
